wekan/__init__.py
wekan/generate.py
wekan-0.1.17.dist-info/METADATA
wekan-0.1.17.dist-info/WHEEL
wekan-0.1.17.dist-info/entry_points.txt
wekan-0.1.17.dist-info/top_level.txt
wekan-0.1.17.dist-info/RECORD
