Metadata-Version: 2.1
Name: wekan
Version: 0.1.17
Summary: Project generator for wekan's python framework
Home-page: https://bitbucket.org/We-Kan-Code/python-backend-framework-generators
Author: Sanchan Moses
Author-email: sanchanm@wekan.company
License: UNKNOWN
Platform: UNKNOWN
Classifier: Programming Language :: Python :: 3
Classifier: License :: OSI Approved :: MIT License
Classifier: Operating System :: OS Independent
Classifier: Environment :: Console
Requires-Python: >=3.6
Requires-Dist: astroid (==2.3.3)
Requires-Dist: autopep8 (==1.5)
Requires-Dist: colorama (==0.4.3)
Requires-Dist: isort (==4.3.21)
Requires-Dist: lazy-object-proxy (==1.4.3)
Requires-Dist: mccabe (==0.6.1)
Requires-Dist: prompt-toolkit (==1.0.14)
Requires-Dist: pycodestyle (==2.5.0)
Requires-Dist: Pygments (==2.5.2)
Requires-Dist: PyInquirer (==1.0.3)
Requires-Dist: pylint (==2.4.4)
Requires-Dist: regex (==2020.1.8)
Requires-Dist: six (==1.14.0)
Requires-Dist: typed-ast (==1.4.1)
Requires-Dist: wcwidth (==0.1.8)
Requires-Dist: wrapt (==1.11.2)
